[
  {
    "station": {
      "id": 1,
      "name": "Radio Mario Maria",
      "shortcode": "rmm1",
      "description": "Transmitiendo desde la frontera Franklin Matta Sur en Santiago \ud83c\udde8\ud83c\uddf1",
      "frontend": "icecast",
      "backend": "liquidsoap",
      "timezone": "America/Santiago",
      "listen_url": "https://tina.radiomariomaria.live:8000/rmm1.256kbps.mp3",
      "url": "https://radiomariomaria.live",
      "public_player_url": "https://tina.radiomariomaria.live/public/rmm1",
      "playlist_pls_url": "https://tina.radiomariomaria.live/public/rmm1/playlist.pls",
      "playlist_m3u_url": "https://tina.radiomariomaria.live/public/rmm1/playlist.m3u",
      "is_public": true,
      "requests_enabled": false,
      "mounts": [
        {
          "id": 1,
          "name": "rmm1 256kbps mp3",
          "url": "https://tina.radiomariomaria.live:8000/rmm1.256kbps.mp3",
          "bitrate": 256,
          "format": "mp3",
          "listeners": {
            "total": 1,
            "unique": 1,
            "current": 1
          },
          "path": "/rmm1.256kbps.mp3",
          "is_default": true
        },
        {
          "id": 3,
          "name": "rmm2 256kbps mp3",
          "url": "https://tina.radiomariomaria.live:8000/rmm2.256kbps.mp3",
          "bitrate": 256,
          "format": "mp3",
          "listeners": {
            "total": 0,
            "unique": 0,
            "current": 0
          },
          "path": "/rmm2.256kbps.mp3",
          "is_default": false
        }
      ],
      "remotes": [],
      "hls_enabled": false,
      "hls_is_default": false,
      "hls_url": null,
      "hls_listeners": 0
    },
    "listeners": {
      "total": 1,
      "unique": 1,
      "current": 1
    },
    "live": {
      "is_live": false,
      "streamer_name": "",
      "broadcast_start": null,
      "art": null
    },
    "now_playing": {
      "sh_id": 259890,
      "played_at": 1784891764,
      "duration": 221,
      "playlist": "RECUENTO_2025",
      "streamer": "",
      "is_request": false,
      "song": {
        "id": "b4d59f255d7c42fcaa0ffea3397f8bec",
        "art": "https://tina.radiomariomaria.live/api/station/rmm1/art/b494cbb9d1970b3d1a395f46-1762991468.jpg",
        "custom_fields": [],
        "text": "Corps Diplomatique - Dans Ta Nuit - Eros Phobia",
        "artist": "Corps Diplomatique",
        "title": "Eros Phobia",
        "album": "Dans Ta Nuit",
        "genre": "",
        "isrc": "",
        "lyrics": ""
      },
      "elapsed": 126,
      "remaining": 95
    },
    "playing_next": {
      "cued_at": 1784891732,
      "played_at": 1784891980,
      "duration": 249.80895,
      "playlist": "RECUENTO_2024",
      "is_request": false,
      "song": {
        "id": "545aa05e7c4b26e143ebeb098b72227f",
        "art": "https://tina.radiomariomaria.live/api/station/rmm1/art/aee2b4ca3a22d9badf6b4a77-1762984893.jpg",
        "custom_fields": [],
        "text": "Rubber Oh - Soil - Bloodlust",
        "artist": "Rubber Oh",
        "title": "Bloodlust",
        "album": "Soil",
        "genre": "",
        "isrc": "",
        "lyrics": ""
      }
    },
    "song_history": [
      {
        "sh_id": 259889,
        "played_at": 1784891737,
        "duration": 29,
        "playlist": "RECUENTO_2024",
        "streamer": "",
        "is_request": false,
        "song": {
          "id": "c45bfe496cefc375b1c8f2859bcb964c",
          "art": "https://tina.radiomariomaria.live/api/station/rmm1/art/8eed3c80498bc499cca58c88-1762985479.jpg",
          "custom_fields": [],
          "text": "Supernatural - Natural Disasters - Boomed Out",
          "artist": "Supernatural",
          "title": "Boomed Out",
          "album": "Natural Disasters",
          "genre": "",
          "isrc": "",
          "lyrics": ""
        }
      }
    ],
    "is_online": true,
    "cache": null
  },
  {
    "station": {
      "id": 2,
      "name": "El Disco es Cultura",
      "shortcode": "eldiscoescultura",
      "description": "Escucha aqu\u00ed gran parte del cat\u00e1logo de discos editados por el sello IRT durante el gobierno de la Unidad Popular en Chile (1970-1973) Proyecto financiado por el Ministerio de las Culturas Folio 767390 ",
      "frontend": "icecast",
      "backend": "liquidsoap",
      "timezone": "America/Santiago",
      "listen_url": "https://tina.radiomariomaria.live:8010/eldiscoescultura.mp3",
      "url": "https://eldiscoescultura.cl",
      "public_player_url": "https://tina.radiomariomaria.live/public/eldiscoescultura",
      "playlist_pls_url": "https://tina.radiomariomaria.live/public/eldiscoescultura/playlist.pls",
      "playlist_m3u_url": "https://tina.radiomariomaria.live/public/eldiscoescultura/playlist.m3u",
      "is_public": true,
      "requests_enabled": false,
      "mounts": [
        {
          "id": 2,
          "name": "/eldiscoescultura.mp3 (192kbps MP3)",
          "url": "https://tina.radiomariomaria.live:8010/eldiscoescultura.mp3",
          "bitrate": 192,
          "format": "mp3",
          "listeners": {
            "total": 1,
            "unique": 1,
            "current": 1
          },
          "path": "/eldiscoescultura.mp3",
          "is_default": true
        }
      ],
      "remotes": [],
      "hls_enabled": false,
      "hls_is_default": false,
      "hls_url": null,
      "hls_listeners": 0
    },
    "listeners": {
      "total": 1,
      "unique": 1,
      "current": 1
    },
    "live": {
      "is_live": false,
      "streamer_name": "",
      "broadcast_start": null,
      "art": null
    },
    "now_playing": {
      "sh_id": 259888,
      "played_at": 1784891627,
      "duration": 317,
      "playlist": "EDEC",
      "streamer": "",
      "is_request": false,
      "song": {
        "id": "9db5304b9c5cff1d56caaf0dd1c46838",
        "art": "https://tina.radiomariomaria.live/api/station/eldiscoescultura/art/7b8bf85978efd0e18166d168",
        "custom_fields": [],
        "text": "Los Tupamaros - Los Tupamaros Cantan - Poemas 8 y 9 - Candombe",
        "artist": "Los Tupamaros",
        "title": "Poemas 8 y 9 - Candombe",
        "album": "Los Tupamaros Cantan",
        "genre": "",
        "isrc": "",
        "lyrics": ""
      },
      "elapsed": 263,
      "remaining": 54
    },
    "playing_next": {
      "cued_at": 1784891411,
      "played_at": 1784891940,
      "duration": 259.082449,
      "playlist": "EDEC",
      "is_request": false,
      "song": {
        "id": "ee2fb38ffdbd744ea736eeb7ba5b9e51",
        "art": "https://tina.radiomariomaria.live/api/station/eldiscoescultura/art/90d93d1ecf2b8431e995970e",
        "custom_fields": [],
        "text": "Valericio Leppe - 29 de Junio de 1973 - El Pueblo Unido Jam\u00e1s Sera Vencido - D\u00e9cimas a la Ma\u00f1ana de San Pedro",
        "artist": "Valericio Leppe",
        "title": "D\u00e9cimas a la Ma\u00f1ana de San Pedro",
        "album": "29 de Junio de 1973 - El Pueblo Unido Jam\u00e1s Sera Vencido",
        "genre": "",
        "isrc": "",
        "lyrics": ""
      }
    },
    "song_history": [
      {
        "sh_id": 259886,
        "played_at": 1784891416,
        "duration": 214,
        "playlist": "EDEC",
        "streamer": "",
        "is_request": false,
        "song": {
          "id": "2ddd6c1cca35dbf122ccc2d7e6637168",
          "art": "https://tina.radiomariomaria.live/api/station/eldiscoescultura/art/d25255e1d456cbfad82afeb5",
          "custom_fields": [],
          "text": "Pedro Y\u00e1\u00f1ez - 29 de Junio de 1973 - El Pueblo Unido Jam\u00e1s Sera Vencido - En La Ma\u00f1ana Del 29",
          "artist": "Pedro Y\u00e1\u00f1ez",
          "title": "En La Ma\u00f1ana Del 29",
          "album": "29 de Junio de 1973 - El Pueblo Unido Jam\u00e1s Sera Vencido",
          "genre": "",
          "isrc": "",
          "lyrics": ""
        }
      },
      {
        "sh_id": 259884,
        "played_at": 1784891278,
        "duration": 149,
        "playlist": "EDEC",
        "streamer": "",
        "is_request": false,
        "song": {
          "id": "e4bd4443f22ca12e67b80c304790804b",
          "art": "https://tina.radiomariomaria.live/api/station/eldiscoescultura/art/fd41c7e86945bf6013913e69-1757470448.jpg",
          "custom_fields": [],
          "text": "El Combo De Pepe - El Combo De Pepe - La Loca Maria",
          "artist": "El Combo De Pepe",
          "title": "La Loca Maria",
          "album": "El Combo De Pepe",
          "genre": "Cumbia peruana\t",
          "isrc": "",
          "lyrics": ""
        }
      },
      {
        "sh_id": 259881,
        "played_at": 1784891044,
        "duration": 234,
        "playlist": "EDEC",
        "streamer": "",
        "is_request": false,
        "song": {
          "id": "9c3a16d6b3f4e85f8f4ec2dd712c277b",
          "art": "https://tina.radiomariomaria.live/api/station/eldiscoescultura/art/84e7834d09b6988128ad9807",
          "custom_fields": [],
          "text": "Patricio Renan - Una vez un ni\u00f1o / Los hijos - Una vez un ni\u00f1o",
          "artist": "Patricio Renan",
          "title": "Una vez un ni\u00f1o",
          "album": "Una vez un ni\u00f1o / Los hijos",
          "genre": "",
          "isrc": "",
          "lyrics": ""
        }
      },
      {
        "sh_id": 259878,
        "played_at": 1784890812,
        "duration": 233,
        "playlist": "EDEC",
        "streamer": "",
        "is_request": false,
        "song": {
          "id": "88bb2b6ec38e00b557697eead8d3ec9b",
          "art": "https://tina.radiomariomaria.live/api/station/eldiscoescultura/art/ca3b39bc03cd5c54760eba67",
          "custom_fields": [],
          "text": "Los Puntillanos - Nos fuimos pa\u00b4sure - Somos chilotes",
          "artist": "Los Puntillanos",
          "title": "Nos fuimos pa\u00b4sure - Somos chilotes",
          "album": "",
          "genre": "",
          "isrc": "",
          "lyrics": ""
        }
      },
      {
        "sh_id": 259875,
        "played_at": 1784890599,
        "duration": 215,
        "playlist": "EDEC",
        "streamer": "",
        "is_request": false,
        "song": {
          "id": "c53c5602bbbe2b1e31f0bfcfee33ba2c",
          "art": "https://tina.radiomariomaria.live/api/station/eldiscoescultura/art/fd0f3ce6f81c4c3b3b65f83c",
          "custom_fields": [],
          "text": "Patricia Maldonado - Como esta / La \u00faltima canci\u00f3n [SINGLE] - LA \u00daLTIMA CANCI\u00d3N",
          "artist": "Patricia Maldonado",
          "title": "LA \u00daLTIMA CANCI\u00d3N",
          "album": "Como esta / La \u00faltima canci\u00f3n [SINGLE]",
          "genre": "",
          "isrc": "",
          "lyrics": ""
        }
      }
    ],
    "is_online": true,
    "cache": null
  },
  {
    "station": {
      "id": 3,
      "name": "Tect\u00f3nica",
      "shortcode": "tectonica",
      "description": "",
      "frontend": "icecast",
      "backend": "liquidsoap",
      "timezone": "America/Santiago",
      "listen_url": "https://tina.radiomariomaria.live:8020/radio.mp3",
      "url": "",
      "public_player_url": "https://tina.radiomariomaria.live/public/tectonica",
      "playlist_pls_url": "https://tina.radiomariomaria.live/public/tectonica/playlist.pls",
      "playlist_m3u_url": "https://tina.radiomariomaria.live/public/tectonica/playlist.m3u",
      "is_public": true,
      "requests_enabled": false,
      "mounts": [
        {
          "id": 5,
          "name": "/radio.mp3 (192kbps MP3)",
          "url": "https://tina.radiomariomaria.live:8020/radio.mp3",
          "bitrate": 192,
          "format": "mp3",
          "listeners": {
            "total": 0,
            "unique": 0,
            "current": 0
          },
          "path": "/radio.mp3",
          "is_default": true
        }
      ],
      "remotes": [],
      "hls_enabled": true,
      "hls_is_default": false,
      "hls_url": "https://tina.radiomariomaria.live/hls/tectonica/live.m3u8",
      "hls_listeners": 0
    },
    "listeners": {
      "total": 0,
      "unique": 0,
      "current": 0
    },
    "live": {
      "is_live": false,
      "streamer_name": "",
      "broadcast_start": null,
      "art": null
    },
    "now_playing": {
      "sh_id": 259891,
      "played_at": 1784891879,
      "duration": 247,
      "playlist": "Especial fines de junio",
      "streamer": "",
      "is_request": false,
      "song": {
        "id": "89c67b91e4d444c57c76fdda2d8769d7",
        "art": "https://tina.radiomariomaria.live/api/station/tectonica/art/6672f4cefce8d6a19da70c87-1781895260.jpg",
        "custom_fields": [],
        "text": "Atlantic Starr - Unknown Album Dance Classics - Let The Sun In",
        "artist": "Atlantic Starr",
        "title": "Let The Sun In",
        "album": "Unknown Album Dance Classics",
        "genre": "Dance Classics",
        "isrc": "",
        "lyrics": ""
      },
      "elapsed": 11,
      "remaining": 236
    },
    "playing_next": {
      "cued_at": 1784891516,
      "played_at": 1784892117,
      "duration": 365.87108221215,
      "playlist": "Especial fines de junio",
      "is_request": false,
      "song": {
        "id": "ebdc9117ec14d31184fc5d52a1db7585",
        "art": "https://tina.radiomariomaria.live/api/station/tectonica/art/ee4c5960d76ce9ad7e8781bd-1781895323.jpg",
        "custom_fields": [],
        "text": "Attitude - Love Me Tonight",
        "artist": "Attitude",
        "title": "Love Me Tonight",
        "album": "",
        "genre": "",
        "isrc": "",
        "lyrics": ""
      }
    },
    "song_history": [
      {
        "sh_id": 259887,
        "played_at": 1784891526,
        "duration": 358,
        "playlist": "Especial fines de junio",
        "streamer": "",
        "is_request": false,
        "song": {
          "id": "b09f2312bfe6c088390594ca363875e8",
          "art": "https://tina.radiomariomaria.live/api/station/tectonica/art/f6dd027ec0c44771a3bc5633-1781895457.jpg",
          "custom_fields": [],
          "text": "Arthur Adams - Unknown Album Dance Classics - You Got The Floor (Original Extended 12'')",
          "artist": "Arthur Adams",
          "title": "You Got The Floor (Original Extended 12'')",
          "album": "Unknown Album Dance Classics",
          "genre": "Dance Classics",
          "isrc": "",
          "lyrics": ""
        }
      },
      {
        "sh_id": 259882,
        "played_at": 1784891121,
        "duration": 405,
        "playlist": "Especial fines de junio",
        "streamer": "",
        "is_request": false,
        "song": {
          "id": "9d124de9c6f13454cfd80d195539a89f",
          "art": "https://tina.radiomariomaria.live/api/station/tectonica/art/05c13060ee28400fbc62cf83-1781895271.jpg",
          "custom_fields": [],
          "text": "Armenta & Majik - Internet Radio - I Wanna Be With You (Long Version)",
          "artist": "Armenta & Majik",
          "title": "I Wanna Be With You (Long Version)",
          "album": "Internet Radio",
          "genre": "Dance Classics",
          "isrc": "",
          "lyrics": ""
        }
      },
      {
        "sh_id": 259877,
        "played_at": 1784890703,
        "duration": 418,
        "playlist": "Especial fines de junio",
        "streamer": "",
        "is_request": false,
        "song": {
          "id": "2e528b729ca50dbf6c429ca4a8f2a66a",
          "art": "https://tina.radiomariomaria.live/api/station/tectonica/art/ac92bce83138aa1bccda2c4b-1781895267.jpg",
          "custom_fields": [],
          "text": "Apollonia 6 - Unknown Album Dance Classics - Sex Shooter (Extended 12'')",
          "artist": "Apollonia 6",
          "title": "Sex Shooter (Extended 12'')",
          "album": "Unknown Album Dance Classics",
          "genre": "Dance Classics",
          "isrc": "",
          "lyrics": ""
        }
      },
      {
        "sh_id": 259872,
        "played_at": 1784890381,
        "duration": 326,
        "playlist": "Especial fines de junio",
        "streamer": "",
        "is_request": false,
        "song": {
          "id": "dbac4666719a917e8c6c832489721b27",
          "art": "https://tina.radiomariomaria.live/api/station/tectonica/art/c6837178161a9d163af35748-1781895700.jpg",
          "custom_fields": [],
          "text": "Aota+Skyscraper - DSR003 - Get It Down",
          "artist": "Aota+Skyscraper",
          "title": "Get It Down",
          "album": "DSR003",
          "genre": "Deep House",
          "isrc": "",
          "lyrics": ""
        }
      },
      {
        "sh_id": 259867,
        "played_at": 1784890029,
        "duration": 355,
        "playlist": "Especial fines de junio",
        "streamer": "",
        "is_request": false,
        "song": {
          "id": "90101703ceebfb666d4bc1bab4ed5868",
          "art": "https://tina.radiomariomaria.live/api/station/tectonica/art/6f0af01c636cb93026a3f114-1781895722.jpg",
          "custom_fields": [],
          "text": "Anthony Franklin - Unknown Album Dance Classics - Hot Number",
          "artist": "Anthony Franklin",
          "title": "Hot Number",
          "album": "Unknown Album Dance Classics",
          "genre": "Dance Classics",
          "isrc": "",
          "lyrics": ""
        }
      }
    ],
    "is_online": true,
    "cache": null
  },
  {
    "station": {
      "id": 4,
      "name": "Tests",
      "shortcode": "tests",
      "description": "",
      "frontend": "icecast",
      "backend": "liquidsoap",
      "timezone": "America/Santiago",
      "listen_url": "https://tina.radiomariomaria.live:8030/radio.mp3",
      "url": "",
      "public_player_url": "https://tina.radiomariomaria.live/public/tests",
      "playlist_pls_url": "https://tina.radiomariomaria.live/public/tests/playlist.pls",
      "playlist_m3u_url": "https://tina.radiomariomaria.live/public/tests/playlist.m3u",
      "is_public": true,
      "requests_enabled": false,
      "mounts": [
        {
          "id": 6,
          "name": "/radio.mp3 (192kbps MP3)",
          "url": "https://tina.radiomariomaria.live:8030/radio.mp3",
          "bitrate": 192,
          "format": "mp3",
          "listeners": {
            "total": 0,
            "unique": 0,
            "current": 0
          },
          "path": "/radio.mp3",
          "is_default": true
        }
      ],
      "remotes": [],
      "hls_enabled": false,
      "hls_is_default": false,
      "hls_url": null,
      "hls_listeners": 0
    },
    "listeners": {
      "total": 0,
      "unique": 0,
      "current": 0
    },
    "live": {
      "is_live": false,
      "streamer_name": "",
      "broadcast_start": null,
      "art": null
    },
    "now_playing": {
      "sh_id": 259505,
      "played_at": 1784862626,
      "duration": 180,
      "playlist": "default",
      "streamer": "",
      "is_request": false,
      "song": {
        "id": "a52ca4cecf717b3606d7bf6a06d785e2",
        "art": "https://tina.radiomariomaria.live/api/station/tests/art/f4d8e2b149107f94a14e60b8",
        "custom_fields": [],
        "text": "Tono - DronCC",
        "artist": "Tono",
        "title": "DronCC",
        "album": "",
        "genre": "",
        "isrc": "",
        "lyrics": ""
      },
      "elapsed": 180,
      "remaining": 0
    },
    "playing_next": {
      "cued_at": 1784851150,
      "played_at": 1784891880,
      "duration": 180.2971,
      "playlist": "default",
      "is_request": false,
      "song": {
        "id": "a52ca4cecf717b3606d7bf6a06d785e2",
        "art": "https://tina.radiomariomaria.live/api/station/tests/art/f4d8e2b149107f94a14e60b8",
        "custom_fields": [],
        "text": "Tono - DronCC",
        "artist": "Tono",
        "title": "DronCC",
        "album": "",
        "genre": "",
        "isrc": "",
        "lyrics": ""
      }
    },
    "song_history": [],
    "is_online": true,
    "cache": null
  }
]